django_coalesce/__init__.py
django_coalesce/__main__.py
django_coalesce/main.py
django_coalesce/models.py
django_coalesce/settings.py
django_coalesce/templatetags/__init__.py
django_coalesce/templatetags/django_coalesce.py
django_coalesce/tests/__init__.py
django_coalesce/tests/test_main.py
django_coalesce-0.0.1.dist-info/LICENSE
django_coalesce-0.0.1.dist-info/METADATA
django_coalesce-0.0.1.dist-info/WHEEL
django_coalesce-0.0.1.dist-info/top_level.txt
django_coalesce-0.0.1.dist-info/RECORD
